ws_ignore_alerts/__init__.py
ws_ignore_alerts/_version.py
ws_ignore_alerts/ignore_alerts.py
ws_ignore_alerts-23.9.2.dist-info/LICENSE
ws_ignore_alerts-23.9.2.dist-info/METADATA
ws_ignore_alerts-23.9.2.dist-info/WHEEL
ws_ignore_alerts-23.9.2.dist-info/entry_points.txt
ws_ignore_alerts-23.9.2.dist-info/top_level.txt
ws_ignore_alerts-23.9.2.dist-info/RECORD
