Metadata-Version: 2.1
Name: ws-ignore-alerts
Version: 23.9.2
Summary: Mend Ignore Alerts
Home-page: https://github.com/whitesource-ps/ws-ignore-alerts
Author: Mend Professional Services
Author-email: ps@whitesourcesoftware.com
License: LICENSE.txt
Platform: UNKNOWN
Classifier: Programming Language :: Python :: 3.7
Classifier: Programming Language :: Python :: 3.8
Classifier: Programming Language :: Python :: 3.9
Classifier: License :: OSI Approved :: Apache Software License
Classifier: Operating System :: OS Independent
Requires-Python: >=3.7
Requires-Dist: configparser ~=5.0.1
Requires-Dist: ws-sdk ~=23.8.3
